{
    "header": {
        "dialogueInfo": {
            "dialogueID": "efe0a199-ef9b-5d5a-a807-f5e85c1befbd",
            "numberOfParticipants": 2,
            "numberOfUtterances": 12,
            "numberOfTurns": 5,
            "source": "한국어SNS",
            "single_topic": "개인 및 관계",
            "multi_topic": [
                "안부/일상_일상공유_소문/루머",
                "안부/일상_일상공유_생각/감정/성향"
            ]
        },
        "participantsInfo": [
            {
                "participantID": "P01",
                "gender": "여성",
                "age": "30대",
                "residentialProvince": "울산광역시"
            },
            {
                "participantID": "P02",
                "gender": "여성",
                "age": "30대",
                "residentialProvince": "서울특별시"
            }
        ]
    },
    "body": [
        {
            "utteranceID": "U01",
            "turnID": "T01",
            "participantID": "P01",
            "date": "2017-02-08",
            "time": "14:19:00",
            "utterance": "지가직접가서 뒤집고 이럴필요가머잇어 솔까"
        },
        {
            "utteranceID": "U02",
            "turnID": "T02",
            "participantID": "P02",
            "date": "2017-02-08",
            "time": "14:19:00",
            "utterance": "아니 금수저면 학교에서 기고 들어가디"
        },
        {
            "utteranceID": "U03",
            "turnID": "T03",
            "participantID": "P01",
            "date": "2017-02-08",
            "time": "14:20:00",
            "utterance": "그거보면서 돈많은 집은아니다 싶엇는데"
        },
        {
            "utteranceID": "U04",
            "turnID": "T03",
            "participantID": "P01",
            "date": "2017-02-08",
            "time": "14:20:00",
            "utterance": "저렇게 지르는거보니"
        },
        {
            "utteranceID": "U05",
            "turnID": "T03",
            "participantID": "P01",
            "date": "2017-02-08",
            "time": "14:20:00",
            "utterance": "진짜 딱 그때 아파트팔아서 이혼하고"
        },
        {
            "utteranceID": "U06",
            "turnID": "T03",
            "participantID": "P01",
            "date": "2017-02-08",
            "time": "14:20:00",
            "utterance": "나머지양육비로주고"
        },
        {
            "utteranceID": "U07",
            "turnID": "T04",
            "participantID": "P02",
            "date": "2017-02-08",
            "time": "14:20:00",
            "utterance": "아니 저돈이면 변호사를 쓸 돈 아니냐"
        },
        {
            "utteranceID": "U08",
            "turnID": "T05",
            "participantID": "P01",
            "date": "2017-02-08",
            "time": "14:20:00",
            "utterance": "몰라 심지어"
        },
        {
            "utteranceID": "U09",
            "turnID": "T05",
            "participantID": "P01",
            "date": "2017-02-08",
            "time": "14:20:00",
            "utterance": "어느정도"
        },
        {
            "utteranceID": "U10",
            "turnID": "T05",
            "participantID": "P01",
            "date": "2017-02-08",
            "time": "14:20:00",
            "utterance": "자기가 해결하고"
        },
        {
            "utteranceID": "U11",
            "turnID": "T05",
            "participantID": "P01",
            "date": "2017-02-08",
            "time": "14:21:00",
            "utterance": "돌려돌려돌려 막다가"
        },
        {
            "utteranceID": "U12",
            "turnID": "T05",
            "participantID": "P01",
            "date": "2017-02-08",
            "time": "14:21:00",
            "utterance": "터진게 오천넘는다누소문이 ㅋㅋㅋㅋ"
        }
    ]
}